categorical_encoder/__init__.py
categorical_encoder/categorical_encoder.py
tests/__init__.py
tests/test_categorical_encoder.py
categorical_encoder_pipeline-0.0.9.dist-info/LICENSE
categorical_encoder_pipeline-0.0.9.dist-info/METADATA
categorical_encoder_pipeline-0.0.9.dist-info/WHEEL
categorical_encoder_pipeline-0.0.9.dist-info/top_level.txt
categorical_encoder_pipeline-0.0.9.dist-info/RECORD
