Metadata-Version: 2.1
Name: categorical-encoder-pipeline
Version: 0.0.9
Summary: Convenient categorical encoder for sklearn pipeline
Home-page: UNKNOWN
Author: Vicent Blanes
Author-email: viblasel@gmail.com
License: UNKNOWN
Platform: UNKNOWN
Classifier: Programming Language :: Python :: 3
Classifier: License :: OSI Approved :: MIT License
Classifier: Operating System :: OS Independent
